LICENSE
cme/__init__.py
cme/cli.py
cme/cmedb.py
cme/connection.py
cme/context.py
cme/crackmapexec.py
cme/data/BloodHound-modified.ps1
cme/data/cme.conf
cme/data/cme.ico
cme/data/default.pem
cme/data/videos_for_darrell.harambe
cme/first_run.py
cme/helpers/__init__.py
cme/helpers/bash.py
cme/helpers/http.py
cme/helpers/logger.py
cme/helpers/misc.py
cme/helpers/powershell.py
cme/loaders/__init__.py
cme/loaders/module_loader.py
cme/loaders/protocol_loader.py
cme/logger.py
cme/modules/Get-ComputerDetails.py
cme/modules/MachineAccountQuota.py
cme/modules/adcs.py
cme/modules/bh_owned.py
cme/modules/bloodhound.py
cme/modules/drop_searchConnector-ms.py
cme/modules/empire_exec.py
cme/modules/enum_avproducts.py
cme/modules/enum_chrome.py
cme/modules/enum_dns.py
cme/modules/example_module.py
cme/modules/get_description.py
cme/modules/get_keystrokes.py
cme/modules/get_netdomaincontroller.py
cme/modules/get_netrdpsession.py
cme/modules/get_timedscreenshot.py
cme/modules/gpp_autologin.py
cme/modules/gpp_password.py
cme/modules/invoke_sessiongopher.py
cme/modules/invoke_vnc.py
cme/modules/laps.py
cme/modules/ldap-signing.py
cme/modules/lsassy_dump.py
cme/modules/met_inject.py
cme/modules/mimikatz.py
cme/modules/mimikatz_enum_chrome.py
cme/modules/mimikatz_enum_vault_creds.py
cme/modules/mimikittenz.py
cme/modules/mimipenguin.py
cme/modules/mssql_priv.py
cme/modules/multirdp.py
cme/modules/netripper.py
cme/modules/pe_inject.py
cme/modules/rdp.py
cme/modules/rid_hijack.py
cme/modules/runasppl.py
cme/modules/scuffy.py
cme/modules/shellcode_inject.py
cme/modules/slinky.py
cme/modules/spider_plus.py
cme/modules/spooler.py
cme/modules/subnets.py
cme/modules/test_connection.py
cme/modules/tokens.py
cme/modules/uac.py
cme/modules/user_description.py
cme/modules/wdigest.py
cme/modules/web_delivery.py
cme/modules/webdav.py
cme/modules/wireless.py
cme/msfrpc.py
cme/parsers/__init__.py
cme/parsers/ip.py
cme/parsers/nessus.py
cme/parsers/nmap.py
cme/protocols/__init__.py
crackmapexec-5.1.9.dist-info/entry_points.txt
crackmapexec-5.1.9.dist-info/LICENSE
crackmapexec-5.1.9.dist-info/WHEEL
crackmapexec-5.1.9.dist-info/METADATA
crackmapexec-5.1.9.dist-info/RECORD
