Metadata-Version: 2.1
Name: crackmapexec
Version: 5.1.9
Summary: A swiss army knife for pentesting networks
Home-page: https://github.com/byt3bl33d3r/CrackMapExec
License: BSD-2-Clause
Author: Marcello Salvati
Author-email: byt3bl33d3r@pm.com
Requires-Python: >=3.7.0,<4.0.0
Classifier: Environment :: Console
Classifier: License :: OSI Approved :: BSD License
Classifier: Programming Language :: Python :: 3
Classifier: Programming Language :: Python :: 3.7
Classifier: Programming Language :: Python :: 3.8
Classifier: Programming Language :: Python :: 3.9
Classifier: Topic :: Security
Requires-Dist: aioconsole (>=0.3.1,<0.4.0)
Requires-Dist: bs4 (>=0.0.1,<0.0.2)
Requires-Dist: impacket (>=0.9.22,<0.10.0)
Requires-Dist: lsassy (>=3.0.0)
Requires-Dist: msgpack (>=1.0.0,<2.0.0)
Requires-Dist: neo4j (>=4.1.1,<5.0.0)
Requires-Dist: paramiko (>=2.7.2,<3.0.0)
Requires-Dist: pylnk3 (>=0.3.0,<0.4.0)
Requires-Dist: pypsrp (>=0.5.0,<0.6.0)
Requires-Dist: pywerview (>=0.3.0,<0.4.0)
Requires-Dist: requests (>=2.9.1)
Requires-Dist: requests-ntlm (>=0.3.0)
Requires-Dist: termcolor (>=1.1.0,<2.0.0)
Requires-Dist: terminaltables (>=3.1.0,<4.0.0)
Requires-Dist: xmltodict (>=0.12.0,<0.13.0)
Project-URL: Repository, https://github.com/byt3bl33d3r/CrackMapExec
